pymwr/__init__.py
pymwr/plot.py
pymwr/read.py
pymwr/utils.py
pymwr-0.1.0.dist-info/METADATA
pymwr-0.1.0.dist-info/WHEEL
pymwr-0.1.0.dist-info/top_level.txt
pymwr-0.1.0.dist-info/RECORD
