Metadata-Version: 2.1
Name: pymwr
Version: 0.1.0
Summary: Python package to interact with MWR data
Home-page: https://github.com/imsayyed/pymwr
Author: Imran Sayyed, Hamid Ali Syed
Author-email: sayyed950@gmail.com, hamidsyed37@gmail.com
Classifier: Programming Language :: Python :: 3
Classifier: License :: OSI Approved :: MIT License
Classifier: Operating System :: OS Independent
Requires-Python: >=3.6
